{
  "generator-jhipster": {
    "blueprints": [
      {
        "name": "generator-jhipster-nodejs",
        "version": "2.0.0"
      }
    ],
    "otherModules": [
      {
        "name": "generator-jhipster-nodejs",
        "version": "2.0.0"
      }
    ],
    "applicationType": "monolith",
    "baseName": "prueba",
    "jhipsterVersion": "7.0.1",
    "skipClient": false,
    "skipServer": false,
    "skipUserManagement": false,
    "skipCheckLengthOfIdentifier": false,
    "skipFakeData": false,
    "jhiPrefix": "jhi",
    "entitySuffix": "",
    "dtoSuffix": "DTO",
    "testFrameworks": [],
    "pages": [],
    "creationTimestamp": 1632886656699,
    "serverPort": "8081",
    "packageName": "com.jhipster.node",
    "databaseType": "mongodb",
    "devDatabaseType": "mongodb",
    "prodDatabaseType": "mongodb",
    "authenticationType": "jwt",
    "clientFramework": "react",
    "withAdminUi": true,
    "clientTheme": "journal",
    "clientThemeVariant": "dark",
    "enableTranslation": false,
    "nativeLanguage": "es",
    "packageFolder": "com/jhipster/node",
    "jwtSecretKey": "OTUzMzgyYjllZWQ5N2VhNDk2MTBmNjE2Y2FiNDIzYzUzZjcxYzlkMDZkMTkyNjU5MzJjZTIxNjA3NTgwM2ZkNGI5YTM3OTExMmFlNWFkNWMwODQ0M2Y1ZmNhNDI1YTU5MWU5NjcxOThlNjQ4ZjI2Yjk3MDkxODcyNzMwYjIwYTQ=",
    "serviceDiscoveryType": false,
    "websocket": false,
    "searchEngine": false,
    "messageBroker": false,
    "enableHibernateCache": false,
    "clientPackageManager": "npm",
    "cacheProvider": "ehcache",
    "buildTool": "maven",
    "reactive": false,
    "languages": ["en", "fr"],
    "entities": ["Paciente", "Medico", "EspecialidadesMedicas", "Turno", "HistoriaClinica", "Diario", "Valoracion", "Historiaclinica"],
    "lastLiquibaseTimestamp": 1632889509000
  }
}
